xsiam_pov_config_check/xsiam_pov_config_check.py
xsiam_pov_config_check-0.2.2.dist-info/METADATA
xsiam_pov_config_check-0.2.2.dist-info/WHEEL
xsiam_pov_config_check-0.2.2.dist-info/entry_points.txt
xsiam_pov_config_check-0.2.2.dist-info/top_level.txt
xsiam_pov_config_check-0.2.2.dist-info/RECORD
