Metadata-Version: 2.4
Name: xsiam-pov-config-check
Version: 0.2.2
Summary: xsiam-pov-config-check
Author-email: Nemanja Miletic <nmiletic@paloaltonetworks.com>
Requires-Python: >=3.8
